astrochem_embedding/__init__.py
astrochem_embedding/__main__.py
astrochem_embedding/utils.py
astrochem_embedding/layers/__init__.py
astrochem_embedding/layers/layers.py
astrochem_embedding/layers/tests/__init__.py
astrochem_embedding/layers/tests/test_layers.py
astrochem_embedding/models/__init__.py
astrochem_embedding/models/layers.py
astrochem_embedding/models/models.py
astrochem_embedding/models/pretrained/VICGAE.pkl
astrochem_embedding/models/pretrained/translator.yml
astrochem_embedding/models/tests/__init__.py
astrochem_embedding/models/tests/test_models.py
astrochem_embedding/pipeline/__init__.py
astrochem_embedding/pipeline/data.py
astrochem_embedding/pipeline/tests/__init__.py
astrochem_embedding/pipeline/tests/test_data.py
astrochem_embedding/tests/__init__.py
astrochem_embedding/tests/test_utils.py
astrochem_embedding-0.2.0.dist-info/LICENSE.rst
astrochem_embedding-0.2.0.dist-info/METADATA
astrochem_embedding-0.2.0.dist-info/WHEEL
astrochem_embedding-0.2.0.dist-info/top_level.txt
astrochem_embedding-0.2.0.dist-info/RECORD
