Metadata-Version: 2.1
Name: astrochem-embedding
Version: 0.2.0
Summary: Language models for astrochemistry
Author-email: Kelvin Lee <kin.long.kelvin.lee@gmail.com>
License: MIT
Keywords: astrochemistry,nlp,self-supervised-learning
Classifier: Development Status :: 1 - Planning
Classifier: Programming Language :: Python :: 3.8
Classifier: Programming Language :: Python :: 3.9
Requires-Python: >=3.8
License-File: LICENSE.rst
Requires-Dist: click (>=8.0.1)
Requires-Dist: palettable (>=3.3.0)
Requires-Dist: wandb (>=0.12.2)
Requires-Dist: torchinfo (>=1.5.3)
Requires-Dist: pytorch-lightning (>=1.4.8)
Requires-Dist: rdkit-pypi (>=2021.9.2)
Requires-Dist: selfies (>=2.0.0)
Requires-Dist: ruamel.yaml (>=0.17.17)
Requires-Dist: scikit-learn (>=1.0.1)
Requires-Dist: pandas (>=1.3.4)
Requires-Dist: torch (>=1.13.1)
Provides-Extra: dev
Requires-Dist: pytest (>=6.2.4) ; extra == 'dev'
Requires-Dist: coverage ; extra == 'dev'
Requires-Dist: safety (>=1.10.3) ; extra == 'dev'
Requires-Dist: flake8 (>=3.9.2) ; extra == 'dev'
Requires-Dist: black (>=21.10b0) ; extra == 'dev'
Requires-Dist: flake8-bandit (>=2.1.2) ; extra == 'dev'
Requires-Dist: flake8-bugbear (>=21.4.3) ; extra == 'dev'
Requires-Dist: flake8-docstrings (>=1.6.0) ; extra == 'dev'
Requires-Dist: pre-commit-hooks (>=4.0.1) ; extra == 'dev'
Requires-Dist: isort ; extra == 'dev'
